{"name":"roblox-ts-game","className":"DataModel","filePaths":["default.project.json"],"children":[{"name":"ReplicatedStorage","className":"ReplicatedStorage","children":[{"name":"rbxts_include","className":"Folder","children":[{"name":"Promise","className":"ModuleScript","filePaths":["include/Promise.lua"]},{"name":"RuntimeLib","className":"ModuleScript","filePaths":["include/RuntimeLib.lua"]},{"name":"node_modules","className":"Folder","children":[{"name":"@rbxts","className":"Folder","children":[{"name":"services","className":"ModuleScript","filePaths":["node_modules/@rbxts/services/init.lua"]}]}]}]}]}]}